adafruit_touchscreen.py
adafruit_circuitpython_touchscreen-1.3.6.dist-info/licenses/LICENSE
adafruit_circuitpython_touchscreen-1.3.6.dist-info/METADATA
adafruit_circuitpython_touchscreen-1.3.6.dist-info/WHEEL
adafruit_circuitpython_touchscreen-1.3.6.dist-info/top_level.txt
adafruit_circuitpython_touchscreen-1.3.6.dist-info/RECORD
