Metadata-Version: 2.4
Name: adafruit-circuitpython-touchscreen
Version: 1.3.6
Summary: CircuitPython library for 4-wire resistive touchscreens
Author-email: Adafruit Industries <circuitpython@adafruit.com>
License: MIT
Project-URL: Homepage, https://github.com/adafruit/Adafruit_CircuitPython_Touchscreen
Keywords: adafruit,blinka,circuitpython,micropython,touchscreen,resistive
Classifier: Intended Audience :: Developers
Classifier: Topic :: Software Development :: Libraries
Classifier: Topic :: Software Development :: Embedded Systems
Classifier: Topic :: System :: Hardware
Classifier: License :: OSI Approved :: MIT License
Classifier: Programming Language :: Python :: 3
License-File: LICENSE
Requires-Dist: Adafruit-Blinka
Provides-Extra: optional
Dynamic: license-file
